tu2k22_judge/__init__.py
tu2k22_judge/constants.py
tu2k22_judge/custom_exceptions.py
tu2k22_judge/log_serializer.py
tu2k22_judge/logger_utils.py
tu2k22_judge/main.py
tu2k22_judge/schema.py
tu2k22_judge/simulator.py
tu2k22_judge-1.0.2.dist-info/entry_points.txt
tu2k22_judge-1.0.2.dist-info/WHEEL
tu2k22_judge-1.0.2.dist-info/METADATA
tu2k22_judge-1.0.2.dist-info/RECORD
