Metadata-Version: 2.1
Name: tu2k22-judge
Version: 1.0.2
Summary: 
Author: Kushal Chordiya
Author-email: kushal.chordiya@trilogy.com
Requires-Python: >=3.7,<4.0
Classifier: Programming Language :: Python :: 3
Classifier: Programming Language :: Python :: 3.10
Classifier: Programming Language :: Python :: 3.7
Classifier: Programming Language :: Python :: 3.8
Classifier: Programming Language :: Python :: 3.9
Requires-Dist: colorama (>=0.4.5,<0.5.0)
Requires-Dist: pydantic (>=1.9.1,<2.0.0)
Requires-Dist: requests (>=2.25.1,<3.0.0)
Requires-Dist: structlog (>=22.1.0,<23.0.0)
Requires-Dist: typer (>=0.6.1,<0.7.0)
